mpd_tpd/cli.py
mpd_tpd-0.2.1.dist-info/LICENSE
mpd_tpd-0.2.1.dist-info/METADATA
mpd_tpd-0.2.1.dist-info/WHEEL
mpd_tpd-0.2.1.dist-info/entry_points.txt
mpd_tpd-0.2.1.dist-info/RECORD
