Metadata-Version: 2.1
Name: mpd-tpd
Version: 0.2.1
Summary: Python command-line tool for helping conceptualise how much money is left until payday
License: GPL-3.0
Author: J-sephB-lt-n
Author-email: joseph.jazz.bolton@gmail.com
Requires-Python: >=3.12,<4.0
Classifier: License :: OSI Approved :: GNU General Public License v3 (GPLv3)
Classifier: Programming Language :: Python :: 3
Classifier: Programming Language :: Python :: 3.12
